mlang/__init__.py
mlang/config.py
mlang/res/__init__.py
mlang/res/corpus.py
mlang/res/vocab.py
mlang-0.1.8.dist-info/DESCRIPTION.rst
mlang-0.1.8.dist-info/METADATA
mlang-0.1.8.dist-info/RECORD
mlang-0.1.8.dist-info/WHEEL
mlang-0.1.8.dist-info/metadata.json
mlang-0.1.8.dist-info/top_level.txt
mlang_client/__init__.py
mlang_client/mclient.py
